{"assets/ca/lets-encrypt-r3.pem":["assets/ca/lets-encrypt-r3.pem"],"assets/fonts/cairo.ttf":["assets/fonts/cairo.ttf"],"assets/fonts/muli/Muli-Bold.ttf":["assets/fonts/muli/Muli-Bold.ttf"],"assets/fonts/muli/Muli.ttf":["assets/fonts/muli/Muli.ttf"],"assets/fonts/notoKufi/NotoKufiArabic-Bold.ttf":["assets/fonts/notoKufi/NotoKufiArabic-Bold.ttf"],"assets/fonts/notoKufi/NotoKufiArabic-Regular.ttf":["assets/fonts/notoKufi/NotoKufiArabic-Regular.ttf"],"assets/fonts/simplified/SimplifiedArabicBold.ttf":["assets/fonts/simplified/SimplifiedArabicBold.ttf"],"assets/fonts/simplified/SimplifiedArabicRegular.ttf":["assets/fonts/simplified/SimplifiedArabicRegular.ttf"],"assets/images/A.jpg":["assets/images/A.jpg"],"assets/images/Frame.svg":["assets/images/Frame.svg"],"assets/images/b.png":["assets/images/b.png"],"assets/images/card.svg":["assets/images/card.svg"],"assets/images/colon.svg":["assets/images/colon.svg"],"assets/images/dash.svg":["assets/images/dash.svg"],"assets/images/dec+.svg":["assets/images/dec+.svg"],"assets/images/dec.svg":["assets/images/dec.svg"],"assets/images/down_arrow.svg":["assets/images/down_arrow.svg"],"assets/images/email.svg":["assets/images/email.svg"],"assets/images/frame.png":["assets/images/frame.png"],"assets/images/icon.png":["assets/images/icon.png"],"assets/images/inc+.svg":["assets/images/inc+.svg"],"assets/images/inc.svg":["assets/images/inc.svg"],"assets/images/info.svg":["assets/images/info.svg"],"assets/images/intro.jpg":["assets/images/intro.jpg"],"assets/images/introImg.svg":["assets/images/introImg.svg"],"assets/images/loading.svg":["assets/images/loading.svg"],"assets/images/logoD.png":["assets/images/logoD.png"],"assets/images/logout.svg":["assets/images/logout.svg"],"assets/images/mobile.svg":["assets/images/mobile.svg"],"assets/images/password.svg":["assets/images/password.svg"],"assets/images/person.svg":["assets/images/person.svg"],"assets/images/point.svg":["assets/images/point.svg"],"assets/images/policy.svg":["assets/images/policy.svg"],"assets/images/right_arrow.svg":["assets/images/right_arrow.svg"],"assets/images/search.svg":["assets/images/search.svg"],"assets/images/star.svg":["assets/images/star.svg"],"assets/images/success.png":["assets/images/success.png"],"assets/images/t.svg":["assets/images/t.svg"],"assets/images/tube.svg":["assets/images/tube.svg"],"assets/images/tube1.svg":["assets/images/tube1.svg"]}